ShujujiegouJiuGaiZheyangXue/README.md
ShujujiegouJiuGaiZheyangXue/__init__.py
ShujujiegouJiuGaiZheyangXue/__main__.py
ShujujiegouJiuGaiZheyangXue/file.epub
ShujujiegouJiuGaiZheyangXue/index.html
ShujujiegouJiuGaiZheyangXue/css/__init__.py
ShujujiegouJiuGaiZheyangXue/css/annotations.css
ShujujiegouJiuGaiZheyangXue/css/main.css
ShujujiegouJiuGaiZheyangXue/css/normalize.css
ShujujiegouJiuGaiZheyangXue/css/popup.css
ShujujiegouJiuGaiZheyangXue/font/__init__.py
ShujujiegouJiuGaiZheyangXue/font/fontello.eot
ShujujiegouJiuGaiZheyangXue/font/fontello.svg
ShujujiegouJiuGaiZheyangXue/font/fontello.ttf
ShujujiegouJiuGaiZheyangXue/font/fontello.woff
ShujujiegouJiuGaiZheyangXue/img/__init__.py
ShujujiegouJiuGaiZheyangXue/img/annotator-glyph-sprite.png
ShujujiegouJiuGaiZheyangXue/img/annotator-icon-sprite.png
ShujujiegouJiuGaiZheyangXue/img/apple-touch-icon.png
ShujujiegouJiuGaiZheyangXue/img/cancelfullscreen.png
ShujujiegouJiuGaiZheyangXue/img/close.png
ShujujiegouJiuGaiZheyangXue/img/fullscreen.png
ShujujiegouJiuGaiZheyangXue/img/loader.gif
ShujujiegouJiuGaiZheyangXue/img/menu-icon.png
ShujujiegouJiuGaiZheyangXue/img/save.png
ShujujiegouJiuGaiZheyangXue/img/saved.png
ShujujiegouJiuGaiZheyangXue/img/settings-s.png
ShujujiegouJiuGaiZheyangXue/img/settings.png
ShujujiegouJiuGaiZheyangXue/img/star.png
ShujujiegouJiuGaiZheyangXue/js/__init__.py
ShujujiegouJiuGaiZheyangXue/js/epub.js
ShujujiegouJiuGaiZheyangXue/js/epub.min.js
ShujujiegouJiuGaiZheyangXue/js/epub.min.map
ShujujiegouJiuGaiZheyangXue/js/hooks.min.js
ShujujiegouJiuGaiZheyangXue/js/hooks.min.map
ShujujiegouJiuGaiZheyangXue/js/reader.js
ShujujiegouJiuGaiZheyangXue/js/reader.js.map
ShujujiegouJiuGaiZheyangXue/js/reader.min.js
ShujujiegouJiuGaiZheyangXue/js/reader.min.map
ShujujiegouJiuGaiZheyangXue/js/hooks/__init__.py
ShujujiegouJiuGaiZheyangXue/js/hooks/extensions/__init__.py
ShujujiegouJiuGaiZheyangXue/js/hooks/extensions/highlight.js
ShujujiegouJiuGaiZheyangXue/js/libs/__init__.py
shujujiegou_jiu_gai_zheyang_xue-2024.3.2.0.dist-info/METADATA
shujujiegou_jiu_gai_zheyang_xue-2024.3.2.0.dist-info/WHEEL
shujujiegou_jiu_gai_zheyang_xue-2024.3.2.0.dist-info/entry_points.txt
shujujiegou_jiu_gai_zheyang_xue-2024.3.2.0.dist-info/top_level.txt
shujujiegou_jiu_gai_zheyang_xue-2024.3.2.0.dist-info/RECORD
